llama_index/storage/kvstore/azure/__init__.py
llama_index/storage/kvstore/azure/base.py
llama_index_storage_kvstore_azure-0.4.1.dist-info/METADATA
llama_index_storage_kvstore_azure-0.4.1.dist-info/WHEEL
llama_index_storage_kvstore_azure-0.4.1.dist-info/licenses/LICENSE
llama_index_storage_kvstore_azure-0.4.1.dist-info/RECORD
