Metadata-Version: 2.4
Name: llama-index-storage-kvstore-azure
Version: 0.4.1
Summary: llama-index kvstore azure integration
Author-email: Fran Aguilera <falven2000@hotmail.com>
License-Expression: MIT
License-File: LICENSE
Requires-Python: <4.0,>=3.9
Requires-Dist: azure-data-tables<13,>=12.5.0
Requires-Dist: llama-index-core<0.15,>=0.13.0
Requires-Dist: llama-index-utils-azure<0.5,>=0.4.0
